AUTHORS
CHANGELOG
LICENSE
MANIFEST.in
README.rst
setup.py
brodul/__init__.py
brodul.recipe.template.egg-info/PKG-INFO
brodul.recipe.template.egg-info/SOURCES.txt
brodul.recipe.template.egg-info/dependency_links.txt
brodul.recipe.template.egg-info/entry_points.txt
brodul.recipe.template.egg-info/namespace_packages.txt
brodul.recipe.template.egg-info/requires.txt
brodul.recipe.template.egg-info/top_level.txt
brodul.recipe.template.egg-info/zip-safe
brodul/recipe/__init__.py
brodul/recipe/template/__init__.py