Metadata-Version: 1.0
Name: brodul.recipe.template
Version: 1.2
Summary: Buildout recipe for making files out of Jinja2 templates
Home-page: http://github.com/brodul/amplecode.recipe.template
Author: Andraz Brodnik
Author-email: brodul@brodul.org
License: BSD
Keywords: zc.buildout recipe template Jinja2
Platform: UNKNOWN
Classifier: Framework :: Buildout
Classifier: Intended Audience :: Developers
Classifier: License :: OSI Approved :: BSD License
Classifier: Programming Language :: Python
Classifier: Topic :: Software Development
Classifier: Topic :: Software Development :: Code Generators
Classifier: Topic :: Software Development :: Pre-processors
